{
  "suggest.noselect": false,
  "diagnostic.displayByAle": true,
  "coc.preferences.formatOnSaveFiletypes": [
    "javascript",
    "typescript",
    "typescriptreact",
    "json",
    "java",
    "javascriptreact",
    "typescript.tsx",
    "graphql",
    "cpp",
    "css",
    "less",
    "scss",
    "graphql",
    "markdown",
    "vue",
    "lua",
    "php",
    "python",
    "ruby",
    "html",
    "swift",
    "solidity",
    "circom",
    "go",
    "haskell",
    "rust"
  ],
  "clangd.path": "~/.config/coc/extensions/coc-clangd-data/install/18.1.3/clangd_18.1.3/bin/clangd",
  "coc.preferences.extensionUpdateCheck": "never",
  "snippets.ultisnips.pythonPrompt": false,
  "workspace.ignoredFolders": [
    "$HOME",
    "$HOME/.cargo/**",
    "$HOME/.rustup/**"
  ],
  "languageserver": {
    "haskell": {
      "command": "haskell-language-server-wrapper",
      "args": [
        "--lsp"
      ],
      "rootPatterns": [
        ".stack.yaml",
        ".hie-bios",
        "BUILD.bazel",
        "cabal.config",
        "package.yaml"
      ],
      "filetypes": [
        "hs",
        "lhs",
        "haskell"
      ]
    }
  },
  "go.goplsOptions": {
    "completeUnimported": true
  }
}
